<Fluid>
	<AccelLimit>	1500.0		</AccelLimit>
	<VelLimit>		100		</VelLimit>
	<Gravity>	0, -10, 0		</Gravity>
	<VolMin> -60, -50, -60 </VolMin>
	<VolMax> 60,  100,  60 </VolMax>

	<GridRes> 128,256,128 </GridRes>

	<SceneId> 2 </SceneId>
</Fluid>




<MultiScene id="2">

	<Name>		Test 	</Name>

	<MaxPNum> 500000 </MaxPNum>
	<MaxTypeNum> 3 </MaxTypeNum>
	<MaxObjNum> 100 </MaxObjNum>
	<SimScale>		1		</SimScale>
	<DT>			0.02  </DT>
	<PSpacing> 1 </PSpacing>
	<SmoothRadius> 2 </SmoothRadius>
	<Gravity>	0, 0,0		</Gravity>

	<Viscosity>	 0.01	</Viscosity>
	<RestDensity> 1.0 </RestDensity>

	<BoundStiff>	1000.0	</BoundStiff>
	<BoundDamp> 0 </BoundDamp>
	<SoftBoundMin>	-50,  00, -50 </SoftBoundMin>
	<SoftBoundMax> 50,   200,  50 </SoftBoundMax>
	
	<DensityRatio> 1,   1,   1  </DensityRatio>
	<ViscRatio>    1,   1,   1   </ViscRatio>
    
    <Vol>
		<VolMin>	-50,  1, -25	</VolMin>
		<VolMax>	 -5, 52, 25	</VolMax>
		<VolFrac>   1,  0,  0 </VolFrac>
	</Vol>

	<!--Vol>
		<VolMin>	-15,  40, -15	</VolMin>
		<VolMax>	15,  70, 15	</VolMax>
		<VolFrac>   1,  0,  0 </VolFrac> 
	</Vol-->
	
	<SurfaceTensionK> 0 </SurfaceTensionK>
	<SurfaceTensionFluidC> 0 </SurfaceTensionFluidC>
	<FBlending> 1 </FBlending>
	
	<!-- PBD Iteration -->

	<MaxIteration> 2 </MaxIteration>
	<stabilizationIterations> 0 </stabilizationIterations>
	<cloth_subiteration> 10 </cloth_subiteration>
	<global_relaxation> 0.35 </global_relaxation>

	

	<!-- Fluid -->

	<PBFepsilon> 5 </PBFepsilon>
	<QFactor>0.3</QFactor>
	
	<k_TensileInstability> 0.1 </k_TensileInstability>
	<n_TensileInstability> 4 </n_TensileInstability>
	
	<VorticityFactor> 0 </VorticityFactor>
	<Pairwise_k> 1 </Pairwise_k>
	<Pairwise_c> 1.5 </Pairwise_c>
	<Surface_Threshold>0.2</Surface_Threshold>
	<Surface_Stiff> 0.01 </Surface_Stiff>
	<Density_Threshold> 1 </Density_Threshold>

	<Anisosupport>1.0</Anisosupport>
	<Anisothres>1.4</Anisothres>
	<Anisothres_coplanar>99</Anisothres_coplanar>


	
	<!-- Cloth -->
	<CollisionStiff> 2 </CollisionStiff>
	<selfcollisionDistance> -1 </selfcollisionDistance>
	<ClothThickness> 0.3 </ClothThickness>
	<collisionDistance> 1.5 </collisionDistance>
	<ClothSelfColDistance> 1 </ClothSelfColDistance>

	<StretchStiff> 0.6 </StretchStiff>
	<CompressStiff> 0.1 </CompressStiff>

	<StretchCompliance>  0.00000001 </StretchCompliance>
	<CompressCompliance> 0.01 </CompressCompliance>
	<BendingStiff> 1 </BendingStiff>
	
	<VolumeStiff> 0.0001 </VolumeStiff>
	<K_damping> 0.99 </K_damping>
	<MaxConstraintNum> 100000 </MaxConstraintNum>
	<MaxTriangleNum> 50000 </MaxTriangleNum>
	<!--restvol> 2476 </restvol-->
	
	


	<PressureEnvironment> 1 </PressureEnvironment>
	<Resistance> 0.0005 </Resistance>
	

	<cloth_porosity> 1 </cloth_porosity>
	<max_saturation> 1.5 </max_saturation>
	<cloth_density> 1 </cloth_density>
	<EmitThres> 1 </EmitThres>

	<diffuseDistance> 1.7 </diffuseDistance>
	<k_absorb> 0 </k_absorb>
	<k_diffuse> 0.1 </k_diffuse>
	<k_diffuse_gravity> 0.01 </k_diffuse_gravity>
	<k_dripBuf> 0.1 </k_dripBuf>

</MultiScene>




